tempfile2/__init__.py
tempfile2-0.1.1.dist-info/LICENSE.md
tempfile2-0.1.1.dist-info/METADATA
tempfile2-0.1.1.dist-info/WHEEL
tempfile2-0.1.1.dist-info/entry_points.txt
tempfile2-0.1.1.dist-info/top_level.txt
tempfile2-0.1.1.dist-info/RECORD
