Metadata-Version: 2.1
Name: tempfile2
Version: 0.1.1
Summary: `tempfile` wrapper
Home-page: https://github.com/excitoon/tempfile2
Author: Vladimir Chebotarev
Author-email: vladimir.chebotarev@gmail.com
License: MIT
Project-URL: Bug Reports, https://github.com/excitoon/tempfile2/issues
Project-URL: Documentation, https://github.com/excitoon/tempfile2/blob/master/README.md
Project-URL: Source, https://github.com/excitoon/tempfile2
Keywords: tempfile
Platform: UNKNOWN
Classifier: Development Status :: 5 - Production/Stable
Classifier: Intended Audience :: Developers
Classifier: Topic :: Software Development :: Libraries
Classifier: Topic :: Software Development :: Libraries :: Python Modules
Classifier: License :: OSI Approved :: MIT License
Classifier: Programming Language :: Python :: 2
Classifier: Programming Language :: Python :: 2.7
Classifier: Programming Language :: Python :: 3
Classifier: Programming Language :: Python :: 3.4
Classifier: Programming Language :: Python :: 3.5
Classifier: Programming Language :: Python :: 3.6
Classifier: Programming Language :: Python :: 3.7
Provides-Extra: dev
Provides-Extra: test
